Timer/CandleTimer.py
Timer/__init__.py
burning_candle/CandleTimer.py
burning_candle/__init__.py
burning_candle/cli.py
burning_candle-1.0.2.dist-info/METADATA
burning_candle-1.0.2.dist-info/WHEEL
burning_candle-1.0.2.dist-info/entry_points.txt
burning_candle-1.0.2.dist-info/top_level.txt
burning_candle-1.0.2.dist-info/RECORD
